venom/__init__.py
venom/test.py
testroger-0.0.2.dist-info/METADATA
testroger-0.0.2.dist-info/WHEEL
testroger-0.0.2.dist-info/top_level.txt
testroger-0.0.2.dist-info/RECORD
