Metadata-Version: 2.1
Name: testroger
Version: 0.0.2
Summary: First one for test
Home-page: UNKNOWN
Author: Florian
Author-email: <mail@mail.com>
License: UNKNOWN
Platform: UNKNOWN
Classifier: Development Status :: 1 - Planning
Classifier: Intended Audience :: Developers
Classifier: Programming Language :: Python :: 3
Classifier: Operating System :: Unix
Classifier: Operating System :: MacOS :: MacOS X
Classifier: Operating System :: Microsoft :: Windows
